gesang/__init__.py
gesang/app.py
gesang/bin/__init__.py
gesang/bin/entry.py
gesang/command/__init__.py
gesang/command/base.py
gesang/command/manage.py
gesang/command/sub_commands/__init__.py
gesang/command/sub_commands/runserver.py
gesang/command/sub_commands/startapp.py
gesang/command/sub_commands/startproject.py
gesang/conf/__init__.py
gesang/conf/default_settings.py
gesang/conf/settings.py
gesang/middleware/__init__.py
gesang/middleware/base.py
gesang/middleware/cors.py
gesang/middleware/gzip.py
gesang/plugin/__init__.py
gesang/plugin/base.py
gesang/tmpl/app/__init__.py-tmpl
gesang/tmpl/app/dbis.py-tmpl
gesang/tmpl/app/models.py-tmpl
gesang/tmpl/app/urls.py-tmpl
gesang/tmpl/app/validators.py-tmpl
gesang/tmpl/app/views.py-tmpl
gesang/tmpl/project/manage.py-tmpl
gesang/tmpl/project/core/__init__.py-tmpl
gesang/tmpl/project/core/settings.py-tmpl
gesang/tmpl/project/core/urls.py-tmpl
gesang/url/__init__.py
gesang/url/conf.py
gesang/utils/__init__.py
gesang/utils/exc.py
gesang/utils/funcs.py
gesang/utils/wraps.py
gesang/validator/__init__.py
gesang/validator/base.py
gesang/view/__init__.py
gesang/view/views.py
gesang-1.0.1.dist-info/LICENSE
gesang-1.0.1.dist-info/METADATA
gesang-1.0.1.dist-info/WHEEL
gesang-1.0.1.dist-info/entry_points.txt
gesang-1.0.1.dist-info/top_level.txt
gesang-1.0.1.dist-info/RECORD
