Metadata-Version: 2.1
Name: gesang
Version: 1.0.1
Summary: A restful api framework with starlette.
Home-page: UNKNOWN
Author: Dong Zhang
Author-email: 785576549@qq.com
License: UNKNOWN
Platform: any
Classifier: Development Status :: 3 - Alpha
Classifier: Programming Language :: Python :: 3.7
Requires-Dist: starlette
Requires-Dist: uvicorn
Requires-Dist: python-multipart
